lamoom/__init__.py
lamoom/ai_models/__init__.py
lamoom/ai_models/ai_model.py
lamoom/ai_models/attempt_to_call.py
lamoom/ai_models/behaviour.py
lamoom/ai_models/claude/__init__.py
lamoom/ai_models/claude/claude_model.py
lamoom/ai_models/claude/constants.py
lamoom/ai_models/claude/responses.py
lamoom/ai_models/constants.py
lamoom/ai_models/openai/__init__.py
lamoom/ai_models/openai/azure_models.py
lamoom/ai_models/openai/exceptions.py
lamoom/ai_models/openai/openai_models.py
lamoom/ai_models/openai/responses.py
lamoom/ai_models/openai/utils.py
lamoom/ai_models/tools/base_tool.py
lamoom/ai_models/tools/errors.py
lamoom/ai_models/tools/web_tool.py
lamoom/ai_models/utils.py
lamoom/exceptions.py
lamoom/prompt/__init__.py
lamoom/prompt/base_prompt.py
lamoom/prompt/chat.py
lamoom/prompt/lamoom.py
lamoom/prompt/prompt.py
lamoom/prompt/user_prompt.py
lamoom/response_parsers/response_parser.py
lamoom/responses.py
lamoom/services/SaveWorker.py
lamoom/services/__init__.py
lamoom/services/lamoom/__init__.py
lamoom/settings.py
lamoom/utils.py
lamoom-0.1.61.dist-info/LICENSE
lamoom-0.1.61.dist-info/METADATA
lamoom-0.1.61.dist-info/WHEEL
lamoom-0.1.61.dist-info/RECORD
