Metadata-Version: 2.3
Name: lamoom
Version: 0.1.61
Summary: 
Author: Lamoom Engineering Team
Author-email: engineering@lamoom.com
Requires-Python: >=3.9,<4.0
Classifier: Programming Language :: Python :: 3
Classifier: Programming Language :: Python :: 3.9
Classifier: Programming Language :: Python :: 3.10
Classifier: Programming Language :: Python :: 3.11
Classifier: Programming Language :: Python :: 3.12
Classifier: Programming Language :: Python :: 3.13
Requires-Dist: anthropic (>=0.31.2,<0.32.0)
Requires-Dist: beautifulsoup4 (>=4.13.4,<5.0.0)
Requires-Dist: httpx (>=0.27.2,<0.28.0)
Requires-Dist: openai (>=1.65.1,<2.0.0)
Requires-Dist: pyyaml (>=6.0.1,<7.0.0)
Requires-Dist: tiktoken (>=0.5.2)
